<!-- TDT DIGITAL -->
<item>
<title>La 1</title>
<link>$doregex[GetPageUrl]</link>
<regex>
<name>GetPageUrl</name>
<expres><![CDATA[#$pyFunction
def GetLSProData(page_data,Cookie_Jar,m,url='http://vercanalestv.com/tv/nacionales/tve-1.html'):
   import liveresolver
   u = liveresolver.resolve(url)
   return u
]]></expres>
<page></page>
<cookieJar></cookieJar>
</regex>
<thumbnail>http://latelete.tv/img/tve1.png</thumbnail>
<fanart>https://raw.githubusercontent.com/Andorth/Hercules/master/imagenes/fanart.jpg</fanart>
</item>
<item>
<title>La 2</title>
<link>$doregex[GetPageUrl]</link>
<regex>
<name>GetPageUrl</name>
<expres><![CDATA[#$pyFunction
def GetLSProData(page_data,Cookie_Jar,m,url='http://vercanalestv.com/tv/nacionales/tve-2.html'):
   import liveresolver
   u = liveresolver.resolve(url)
   return u
]]></expres>
<page></page>
<cookieJar></cookieJar>
</regex>
<thumbnail>http://latelete.tv/img/tve2.png</thumbnail>
<fanart>https://raw.githubusercontent.com/Andorth/Hercules/master/imagenes/fanart.jpg</fanart>
</item>
<item>
<title>Antena 3</title>
<link>$doregex[GetPageUrl]</link>
<regex>
<name>GetPageUrl</name>
<expres><![CDATA[#$pyFunction
def GetLSProData(page_data,Cookie_Jar,m,url='http://vercanalestv.com/tv/nacionales/antena-3.html'):
   import liveresolver
   u = liveresolver.resolve(url)
   return u
]]></expres>
<page></page>
<cookieJar></cookieJar>
</regex>
<thumbnail>http://latelete.tv/img/antena3.png</thumbnail>
<fanart>https://raw.githubusercontent.com/Andorth/Hercules/master/imagenes/fanart.jpg</fanart>
</item>
<item>
<title>Cuatro</title>
<link>$doregex[GetPageUrl]</link>
<regex>
<name>GetPageUrl</name>
<expres><![CDATA[#$pyFunction
def GetLSProData(page_data,Cookie_Jar,m,url='http://vercanalestv.com/tv/nacionales/cuatro.html'):
   import liveresolver
   u = liveresolver.resolve(url)
   return u
]]></expres>
<page></page>
<cookieJar></cookieJar>
</regex>
<thumbnail>http://latelete.tv/img/cuatro.png</thumbnail>
<fanart>https://raw.githubusercontent.com/Andorth/Hercules/master/imagenes/fanart.jpg</fanart>
</item>

<item>
<title>Tele cinco</title>
<link>$doregex[GetPageUrl]</link>
<regex>
<name>GetPageUrl</name>
<expres><![CDATA[#$pyFunction
def GetLSProData(page_data,Cookie_Jar,m,url='http://vercanalestv.com/tv/nacionales/telecinco.html'):
   import liveresolver
   u = liveresolver.resolve(url)
   return u
]]></expres>
<page></page>
<cookieJar></cookieJar>
</regex>
<thumbnail>http://latelete.tv/img/telecinco.png</thumbnail>
<fanart>https://raw.githubusercontent.com/Andorth/Hercules/master/imagenes/fanart.jpg</fanart>
</item>

<item>
<title>La sexta</title>
<link>$doregex[GetPageUrl]</link>
<regex>
<name>GetPageUrl</name>
<expres><![CDATA[#$pyFunction
def GetLSProData(page_data,Cookie_Jar,m,url='http://vercanalestv.com/tv/nacionales/la-sexta.html'):
   import liveresolver
   u = liveresolver.resolve(url)
   return u
]]></expres>
<page></page>
<cookieJar></cookieJar>
</regex>
<thumbnail>http://latelete.tv/img/sexta.png</thumbnail>
<fanart>https://raw.githubusercontent.com/Andorth/Hercules/master/imagenes/fanart.jpg</fanart>
</item>

<item>
<title>Nova</title>
<link>$doregex[GetPageUrl]</link>
<regex>
<name>GetPageUrl</name>
<expres><![CDATA[#$pyFunction
def GetLSProData(page_data,Cookie_Jar,m,url='http://vercanalestv.com/tv/nacionales/nova.html'):
   import liveresolver
   u = liveresolver.resolve(url)
   return u
]]></expres>
<page></page>
<cookieJar></cookieJar>
</regex>
<thumbnail>http://latelete.tv/img/nova.png</thumbnail>
<fanart>https://raw.githubusercontent.com/Andorth/Hercules/master/imagenes/fanart.jpg</fanart>
</item>

<item>
<title>Divinity</title>
<link>$doregex[GetPageUrl]</link>
<regex>
<name>GetPageUrl</name>
<expres><![CDATA[#$pyFunction
def GetLSProData(page_data,Cookie_Jar,m,url='http://vercanalestv.com/tv/nacionales/divinity.html'):
   import liveresolver
   u = liveresolver.resolve(url)
   return u
]]></expres>
<page></page>
<cookieJar></cookieJar>
</regex>
<thumbnail>http://latelete.tv/img/divinity.png</thumbnail>
<fanart>https://raw.githubusercontent.com/Andorth/Hercules/master/imagenes/fanart.jpg</fanart>
</item>

<item>
<title>A3Series</title>
<link>$doregex[GetPageUrl]</link>
<regex>
<name>GetPageUrl</name>
<expres><![CDATA[#$pyFunction
def GetLSProData(page_data,Cookie_Jar,m,url='http://www.vercanalestv.com/tv/nacionales/atreseries.html'):
   import liveresolver
   u = liveresolver.resolve(url)
   return u
]]></expres>
<page></page>
<cookieJar></cookieJar>
</regex>
<thumbnail>http://latelete.tv/img/atreseries.png</thumbnail>
<fanart>https://raw.githubusercontent.com/Andorth/Hercules/master/imagenes/fanart.jpg</fanart>
</item>

<item>
<title>BeMad</title>
<link>$doregex[GetPageUrl]</link>
<regex>
<name>GetPageUrl</name>
<expres><![CDATA[#$pyFunction
def GetLSProData(page_data,Cookie_Jar,m,url='http://vercanalestv.com/tv/nacionales/be-mad.html'):
   import liveresolver
   u = liveresolver.resolve(url)
   return u
]]></expres>
<page></page>
<cookieJar></cookieJar>
</regex>
<thumbnail>http://latelete.tv/img/bemad.png</thumbnail>
<fanart>https://raw.githubusercontent.com/Andorth/Hercules/master/imagenes/fanart.jpg</fanart>
</item>

<item>
<title>Energy</title>
<link>$doregex[GetPageUrl]</link>
<regex>
<name>GetPageUrl</name>
<expres><![CDATA[#$pyFunction
def GetLSProData(page_data,Cookie_Jar,m,url='http://vercanalestv.com/tv/nacionales/energy.html'):
   import liveresolver
   u = liveresolver.resolve(url)
   return u
]]></expres>
<page></page>
<cookieJar></cookieJar>
</regex>
<thumbnail>http://latelete.tv/img/energy.png</thumbnail>
<fanart>https://raw.githubusercontent.com/Andorth/Hercules/master/imagenes/fanart.jpg</fanart>
</item>

<item>
<title>Dkiss</title>
<link>$doregex[GetPageUrl]</link>
<regex>
<name>GetPageUrl</name>
<expres><![CDATA[#$pyFunction
def GetLSProData(page_data,Cookie_Jar,m,url='http://cinestrenostv.tv/canales/embed/nacionales/dkiss.html'):
   import liveresolver
   u = liveresolver.resolve(url)
   return u
]]></expres>
<page></page>
<cookieJar></cookieJar>
</regex>
<thumbnail>http://latelete.tv/img/dkiss.png</thumbnail>
<fanart>https://raw.githubusercontent.com/Andorth/Hercules/master/imagenes/fanart.jpg</fanart>
</item>





<!-- MOVISTAR PLUS-->
<!-- INTERNACIONAL -->
<!-- DEPORTES -->
<item>
<title>National Geographic</title>
<link>$doregex[GetPageUrl]</link>
<regex>
<name>GetPageUrl</name>
<expres><![CDATA[#$pyFunction
def GetLSProData(page_data,Cookie_Jar,m,url='http://vercanalestv.com/tv/documentales/national-geographic.html'):
   import liveresolver
   u = liveresolver.resolve(url)
   return u
]]></expres>
<page></page>
<cookieJar></cookieJar>
</regex>
<fanart>https://raw.githubusercontent.com/Andorth/Hercules/master/imagenes/fanart.jpg</fanart>
</item>

<item>
<title>#0</title>
<link>$doregex[GetPageUrl]</link>
<regex>
<name>GetPageUrl</name>
<expres><![CDATA[#$pyFunction
def GetLSProData(page_data,Cookie_Jar,m,url='http://vercanalestv.com/tv/nacionales/canal-plus-1.html'):
   import liveresolver
   u = liveresolver.resolve(url)
   return u
]]></expres>
<page></page>
<cookieJar></cookieJar>
</regex>
<fanart>https://raw.githubusercontent.com/Andorth/Hercules/master/imagenes/fanart.jpg</fanart>
</item>